<OwnedCarTrans><CustomCar><BaseCar>56320</BaseCar><CarClassHash>415909161</CarClassHash><Id>0</Id><IsPreset>true</IsPreset><Level>0</Level><Name>preset_rx7_style4</Name><Paints><CustomPaintTrans><Group>1419025149</Group><Hue>496032328</Hue><Sat>0</Sat><Slot>0</Slot><Var>255</Var></CustomPaintTrans><CustomPaintTrans><Group>357200846</Group><Hue>496032591</Hue><Sat>255</Sat><Slot>1</Slot><Var>170</Var></CustomPaintTrans><CustomPaintTrans><Group>357200846</Group><Hue>496032591</Hue><Sat>255</Sat><Slot>2</Slot><Var>170</Var></CustomPaintTrans><CustomPaintTrans><Group>1419025149</Group><Hue>496032328</Hue><Sat>0</Sat><Slot>3</Slot><Var>255</Var></CustomPaintTrans><CustomPaintTrans><Group>1419025149</Group><Hue>496032328</Hue><Sat>0</Sat><Slot>4</Slot><Var>255</Var></CustomPaintTrans><CustomPaintTrans><Group>1419025149</Group><Hue>496032328</Hue><Sat>0</Sat><Slot>5</Slot><Var>255</Var></CustomPaintTrans><CustomPaintTrans><Group>1419025149</Group><Hue>496032328</Hue><Sat>0</Sat><Slot>6</Slot><Var>255</Var></CustomPaintTrans><CustomPaintTrans><Group>1419025149</Group><Hue>496032328</Hue><Sat>0</Sat><Slot>7</Slot><Var>255</Var></CustomPaintTrans></Paints><PerformanceParts/><PhysicsProfileHash>-1911961549</PhysicsProfileHash><Rating>1</Rating><ResalePrice>0</ResalePrice><RideHeightDrop>0</RideHeightDrop><SkillModParts/><SkillModSlotCount>5</SkillModSlotCount><Version>0</Version><Vinyls><CustomVinylTrans><Hash>1881678325</Hash><Hue1>-799662186</Hue1><Hue2>-799662215</Hue2><Hue3>0</Hue3><Hue4>0</Hue4><Layer>0</Layer><Mir>true</Mir><Rot>63</Rot><Sat1>255</Sat1><Sat2>0</Sat2><Sat3>0</Sat3><Sat4>0</Sat4><ScaleX>4915</ScaleX><ScaleY>654</ScaleY><Shear>0</Shear><TranX>414</TranX><TranY>0</TranY><Var1>255</Var1><Var2>72</Var2><Var3>0</Var3><Var4>0</Var4></CustomVinylTrans><CustomVinylTrans><Hash>1881678325</Hash><Hue1>0</Hue1><Hue2>0</Hue2><Hue3>0</Hue3><Hue4>0</Hue4><Layer>1</Layer><Mir>false</Mir><Rot>0</Rot><Sat1>0</Sat1><Sat2>0</Sat2><Sat3>0</Sat3><Sat4>0</Sat4><ScaleX>4914</ScaleX><ScaleY>393</ScaleY><Shear>0</Shear><TranX>204</TranX><TranY>-462</TranY><Var1>0</Var1><Var2>0</Var2><Var3>0</Var3><Var4>0</Var4></CustomVinylTrans><CustomVinylTrans><Hash>-456206930</Hash><Hue1>-799662420</Hue1><Hue2>0</Hue2><Hue3>0</Hue3><Hue4>0</Hue4><Layer>2</Layer><Mir>false</Mir><Rot>64</Rot><Sat1>0</Sat1><Sat2>0</Sat2><Sat3>0</Sat3><Sat4>0</Sat4><ScaleX>163</ScaleX><ScaleY>131</ScaleY><Shear>0</Shear><TranX>254</TranX><TranY>-128</TranY><Var1>139</Var1><Var2>0</Var2><Var3>0</Var3><Var4>0</Var4></CustomVinylTrans><CustomVinylTrans><Hash>-456206930</Hash><Hue1>0</Hue1><Hue2>0</Hue2><Hue3>0</Hue3><Hue4>0</Hue4><Layer>3</Layer><Mir>false</Mir><Rot>193</Rot><Sat1>0</Sat1><Sat2>0</Sat2><Sat3>0</Sat3><Sat4>0</Sat4><ScaleX>163</ScaleX><ScaleY>131</ScaleY><Shear>0</Shear><TranX>-252</TranX><TranY>-128</TranY><Var1>0</Var1><Var2>0</Var2><Var3>0</Var3><Var4>0</Var4></CustomVinylTrans><CustomVinylTrans><Hash>-320039711</Hash><Hue1>-799662415</Hue1><Hue2>-799662420</Hue2><Hue3>0</Hue3><Hue4>0</Hue4><Layer>4</Layer><Mir>false</Mir><Rot>64</Rot><Sat1>0</Sat1><Sat2>0</Sat2><Sat3>0</Sat3><Sat4>0</Sat4><ScaleX>131</ScaleX><ScaleY>131</ScaleY><Shear>0</Shear><TranX>384</TranX><TranY>-80</TranY><Var1>193</Var1><Var2>151</Var2><Var3>0</Var3><Var4>0</Var4></CustomVinylTrans><CustomVinylTrans><Hash>-320039711</Hash><Hue1>-799662420</Hue1><Hue2>-799662447</Hue2><Hue3>0</Hue3><Hue4>0</Hue4><Layer>5</Layer><Mir>false</Mir><Rot>192</Rot><Sat1>0</Sat1><Sat2>0</Sat2><Sat3>0</Sat3><Sat4>0</Sat4><ScaleX>131</ScaleX><ScaleY>131</ScaleY><Shear>0</Shear><TranX>-384</TranX><TranY>-80</TranY><Var1>170</Var1><Var2>139</Var2><Var3>0</Var3><Var4>0</Var4></CustomVinylTrans><CustomVinylTrans><Hash>-448310689</Hash><Hue1>-799662416</Hue1><Hue2>-799662353</Hue2><Hue3>0</Hue3><Hue4>0</Hue4><Layer>6</Layer><Mir>false</Mir><Rot>64</Rot><Sat1>0</Sat1><Sat2>0</Sat2><Sat3>0</Sat3><Sat4>0</Sat4><ScaleX>107</ScaleX><ScaleY>124</ScaleY><Shear>0</Shear><TranX>307</TranX><TranY>-112</TranY><Var1>139</Var1><Var2>139</Var2><Var3>0</Var3><Var4>0</Var4></CustomVinylTrans><CustomVinylTrans><Hash>-448310689</Hash><Hue1>-799662385</Hue1><Hue2>-799662444</Hue2><Hue3>0</Hue3><Hue4>0</Hue4><Layer>7</Layer><Mir>false</Mir><Rot>192</Rot><Sat1>0</Sat1><Sat2>0</Sat2><Sat3>0</Sat3><Sat4>0</Sat4><ScaleX>107</ScaleX><ScaleY>124</ScaleY><Shear>0</Shear><TranX>-306</TranX><TranY>-111</TranY><Var1>139</Var1><Var2>139</Var2><Var3>0</Var3><Var4>0</Var4></CustomVinylTrans><CustomVinylTrans><Hash>-1211016462</Hash><Hue1>-799662379</Hue1><Hue2>-799662414</Hue2><Hue3>0</Hue3><Hue4>0</Hue4><Layer>8</Layer><Mir>true</Mir><Rot>64</Rot><Sat1>0</Sat1><Sat2>0</Sat2><Sat3>0</Sat3><Sat4>0</Sat4><ScaleX>138</ScaleX><ScaleY>245</ScaleY><Shear>0</Shear><TranX>281</TranX><TranY>-128</TranY><Var1>132</Var1><Var2>226</Var2><Var3>0</Var3><Var4>0</Var4></CustomVinylTrans><CustomVinylTrans><Hash>2013817142</Hash><Hue1>0</Hue1><Hue2>-799662217</Hue2><Hue3>0</Hue3><Hue4>0</Hue4><Layer>9</Layer><Mir>false</Mir><Rot>64</Rot><Sat1>0</Sat1><Sat2>0</Sat2><Sat3>0</Sat3><Sat4>0</Sat4><ScaleX>96</ScaleX><ScaleY>163</ScaleY><Shear>0</Shear><TranX>347</TranX><TranY>-99</TranY><Var1>0</Var1><Var2>139</Var2><Var3>0</Var3><Var4>0</Var4></CustomVinylTrans><CustomVinylTrans><Hash>2013817142</Hash><Hue1>0</Hue1><Hue2>-799662312</Hue2><Hue3>0</Hue3><Hue4>0</Hue4><Layer>10</Layer><Mir>false</Mir><Rot>192</Rot><Sat1>0</Sat1><Sat2>0</Sat2><Sat3>0</Sat3><Sat4>0</Sat4><ScaleX>96</ScaleX><ScaleY>163</ScaleY><Shear>0</Shear><TranX>-347</TranX><TranY>-99</TranY><Var1>0</Var1><Var2>139</Var2><Var3>0</Var3><Var4>0</Var4></CustomVinylTrans></Vinyls><VisualParts><VisualPartTrans><PartHash>-1986763776</PartHash><SlotHash>453545749</SlotHash></VisualPartTrans><VisualPartTrans><PartHash>-200501130</PartHash><SlotHash>-966088147</SlotHash></VisualPartTrans><VisualPartTrans><PartHash>-1043723411</PartHash><SlotHash>-918850563</SlotHash></VisualPartTrans><VisualPartTrans><PartHash>-273819714</PartHash><SlotHash>-2126743923</SlotHash></VisualPartTrans><VisualPartTrans><PartHash>-1412840107</PartHash><SlotHash>-1505530948</SlotHash></VisualPartTrans><VisualPartTrans><PartHash>-370788063</PartHash><SlotHash>1490249</SlotHash></VisualPartTrans></VisualParts></CustomCar><Durability>100</Durability><ExpirationDate/><Heat>1</Heat><Id>0</Id><OwnershipType>PresetCar</OwnershipType></OwnedCarTrans>