<OwnedCarTrans>
	<CustomCar>
		<BaseCar>1095591178</BaseCar>
		<CarClassHash>-405837480</CarClassHash>
		<Id>16104745</Id>
		<IsPreset>true</IsPreset>
		<Level>0</Level>
		<Name>terlingua</Name>
		<Paints>
			<CustomPaintTrans>
				<Group>47885063</Group>
				<Hue>496032395</Hue>
				<Sat>0</Sat>
				<Slot>0</Slot>
				<Var>0</Var>
			</CustomPaintTrans>
			<CustomPaintTrans>
				<Group>-1480403439</Group>
				<Hue>496032328</Hue>
				<Sat>0</Sat>
				<Slot>1</Slot>
				<Var>0</Var>
			</CustomPaintTrans>
			<CustomPaintTrans>
				<Group>-1480403439</Group>
				<Hue>496032328</Hue>
				<Sat>0</Sat>
				<Slot>2</Slot>
				<Var>0</Var>
			</CustomPaintTrans>
			<CustomPaintTrans>
				<Group>47885063</Group>
				<Hue>496032395</Hue>
				<Sat>0</Sat>
				<Slot>3</Slot>
				<Var>0</Var>
			</CustomPaintTrans>
			<CustomPaintTrans>
				<Group>47885063</Group>
				<Hue>496032395</Hue>
				<Sat>0</Sat>
				<Slot>4</Slot>
				<Var>0</Var>
			</CustomPaintTrans>
			<CustomPaintTrans>
				<Group>47885063</Group>
				<Hue>496032395</Hue>
				<Sat>0</Sat>
				<Slot>5</Slot>
				<Var>0</Var>
			</CustomPaintTrans>
			<CustomPaintTrans>
				<Group>47885063</Group>
				<Hue>496032395</Hue>
				<Sat>0</Sat>
				<Slot>6</Slot>
				<Var>0</Var>
			</CustomPaintTrans>
			<CustomPaintTrans>
				<Group>47885063</Group>
				<Hue>496032395</Hue>
				<Sat>0</Sat>
				<Slot>7</Slot>
				<Var>0</Var>
			</CustomPaintTrans>
		</Paints>
		<PerformanceParts>
			<PerformancePartTrans>
				<PerformancePartAttribHash>-1586660062</PerformancePartAttribHash>
			</PerformancePartTrans>
			<PerformancePartTrans>
				<PerformancePartAttribHash>-1481726974</PerformancePartAttribHash>
			</PerformancePartTrans>
			<PerformancePartTrans>
				<PerformancePartAttribHash>-1432021954</PerformancePartAttribHash>
			</PerformancePartTrans>
			<PerformancePartTrans>
				<PerformancePartAttribHash>-880514079</PerformancePartAttribHash>
			</PerformancePartTrans>
			<PerformancePartTrans>
				<PerformancePartAttribHash>-711274200</PerformancePartAttribHash>
			</PerformancePartTrans>
			<PerformancePartTrans>
				<PerformancePartAttribHash>-595069127</PerformancePartAttribHash>
			</PerformancePartTrans>
		</PerformanceParts>
		<PhysicsProfileHash>-995782761</PhysicsProfileHash>
		<Rating>650</Rating>
		<ResalePrice>315000</ResalePrice>
		<RideHeightDrop>0</RideHeightDrop>
		<SkillModParts/>
		<SkillModSlotCount>6</SkillModSlotCount>
		<Version>0</Version>
		<Vinyls>
			<CustomVinylTrans>
				<Hash>1354595734</Hash>
				<Hue1>0</Hue1>
				<Hue2>0</Hue2>
				<Hue3>0</Hue3>
				<Hue4>0</Hue4>
				<Layer>0</Layer>
				<Mir>false</Mir>
				<Rot>0</Rot>
				<Sat1>0</Sat1>
				<Sat2>0</Sat2>
				<Sat3>0</Sat3>
				<Sat4>0</Sat4>
				<ScaleX>884</ScaleX>
				<ScaleY>884</ScaleY>
				<Shear>0</Shear>
				<TranX>-340</TranX>
				<TranY>-1</TranY>
				<Var1>0</Var1>
				<Var2>0</Var2>
				<Var3>0</Var3>
				<Var4>0</Var4>
			</CustomVinylTrans>
			<CustomVinylTrans>
				<Hash>1368826786</Hash>
				<Hue1>0</Hue1>
				<Hue2>0</Hue2>
				<Hue3>0</Hue3>
				<Hue4>0</Hue4>
				<Layer>1</Layer>
				<Mir>false</Mir>
				<Rot>0</Rot>
				<Sat1>0</Sat1>
				<Sat2>0</Sat2>
				<Sat3>0</Sat3>
				<Sat4>0</Sat4>
				<ScaleX>883</ScaleX>
				<ScaleY>883</ScaleY>
				<Shear>0</Shear>
				<TranX>340</TranX>
				<TranY>-1</TranY>
				<Var1>0</Var1>
				<Var2>0</Var2>
				<Var3>0</Var3>
				<Var4>0</Var4>
			</CustomVinylTrans>
			<CustomVinylTrans>
				<Hash>1354595735</Hash>
				<Hue1>0</Hue1>
				<Hue2>0</Hue2>
				<Hue3>0</Hue3>
				<Hue4>0</Hue4>
				<Layer>2</Layer>
				<Mir>false</Mir>
				<Rot>0</Rot>
				<Sat1>0</Sat1>
				<Sat2>0</Sat2>
				<Sat3>0</Sat3>
				<Sat4>0</Sat4>
				<ScaleX>1605</ScaleX>
				<ScaleY>1605</ScaleY>
				<Shear>0</Shear>
				<TranX>-225</TranX>
				<TranY>99</TranY>
				<Var1>0</Var1>
				<Var2>0</Var2>
				<Var3>0</Var3>
				<Var4>0</Var4>
			</CustomVinylTrans>
			<CustomVinylTrans>
				<Hash>1368826787</Hash>
				<Hue1>0</Hue1>
				<Hue2>0</Hue2>
				<Hue3>0</Hue3>
				<Hue4>0</Hue4>
				<Layer>3</Layer>
				<Mir>false</Mir>
				<Rot>0</Rot>
				<Sat1>0</Sat1>
				<Sat2>0</Sat2>
				<Sat3>0</Sat3>
				<Sat4>0</Sat4>
				<ScaleX>1605</ScaleX>
				<ScaleY>1605</ScaleY>
				<Shear>0</Shear>
				<TranX>224</TranX>
				<TranY>99</TranY>
				<Var1>0</Var1>
				<Var2>0</Var2>
				<Var3>0</Var3>
				<Var4>0</Var4>
			</CustomVinylTrans>
			<CustomVinylTrans>
				<Hash>1354595736</Hash>
				<Hue1>0</Hue1>
				<Hue2>0</Hue2>
				<Hue3>0</Hue3>
				<Hue4>0</Hue4>
				<Layer>4</Layer>
				<Mir>false</Mir>
				<Rot>0</Rot>
				<Sat1>0</Sat1>
				<Sat2>0</Sat2>
				<Sat3>0</Sat3>
				<Sat4>0</Sat4>
				<ScaleX>573</ScaleX>
				<ScaleY>573</ScaleY>
				<Shear>0</Shear>
				<TranX>-204</TranX>
				<TranY>-220</TranY>
				<Var1>0</Var1>
				<Var2>0</Var2>
				<Var3>0</Var3>
				<Var4>0</Var4>
			</CustomVinylTrans>
			<CustomVinylTrans>
				<Hash>1368826788</Hash>
				<Hue1>0</Hue1>
				<Hue2>0</Hue2>
				<Hue3>0</Hue3>
				<Hue4>0</Hue4>
				<Layer>5</Layer>
				<Mir>false</Mir>
				<Rot>0</Rot>
				<Sat1>0</Sat1>
				<Sat2>0</Sat2>
				<Sat3>0</Sat3>
				<Sat4>0</Sat4>
				<ScaleX>573</ScaleX>
				<ScaleY>573</ScaleY>
				<Shear>0</Shear>
				<TranX>204</TranX>
				<TranY>-220</TranY>
				<Var1>0</Var1>
				<Var2>0</Var2>
				<Var3>0</Var3>
				<Var4>0</Var4>
			</CustomVinylTrans>
			<CustomVinylTrans>
				<Hash>1328074917</Hash>
				<Hue1>0</Hue1>
				<Hue2>0</Hue2>
				<Hue3>0</Hue3>
				<Hue4>0</Hue4>
				<Layer>6</Layer>
				<Mir>false</Mir>
				<Rot>0</Rot>
				<Sat1>0</Sat1>
				<Sat2>0</Sat2>
				<Sat3>0</Sat3>
				<Sat4>0</Sat4>
				<ScaleX>1900</ScaleX>
				<ScaleY>1998</ScaleY>
				<Shear>0</Shear>
				<TranX>-1</TranX>
				<TranY>-220</TranY>
				<Var1>0</Var1>
				<Var2>0</Var2>
				<Var3>0</Var3>
				<Var4>0</Var4>
			</CustomVinylTrans>
			<CustomVinylTrans>
				<Hash>1328075112</Hash>
				<Hue1>0</Hue1>
				<Hue2>0</Hue2>
				<Hue3>0</Hue3>
				<Hue4>0</Hue4>
				<Layer>7</Layer>
				<Mir>false</Mir>
				<Rot>0</Rot>
				<Sat1>0</Sat1>
				<Sat2>0</Sat2>
				<Sat3>0</Sat3>
				<Sat4>0</Sat4>
				<ScaleX>753</ScaleX>
				<ScaleY>753</ScaleY>
				<Shear>0</Shear>
				<TranX>0</TranX>
				<TranY>276</TranY>
				<Var1>0</Var1>
				<Var2>0</Var2>
				<Var3>0</Var3>
				<Var4>0</Var4>
			</CustomVinylTrans>
			<CustomVinylTrans>
				<Hash>-456206930</Hash>
				<Hue1>-799662189</Hue1>
				<Hue2>0</Hue2>
				<Hue3>0</Hue3>
				<Hue4>0</Hue4>
				<Layer>8</Layer>
				<Mir>false</Mir>
				<Rot>0</Rot>
				<Sat1>255</Sat1>
				<Sat2>0</Sat2>
				<Sat3>0</Sat3>
				<Sat4>0</Sat4>
				<ScaleX>163</ScaleX>
				<ScaleY>163</ScaleY>
				<Shear>0</Shear>
				<TranX>0</TranX>
				<TranY>-117</TranY>
				<Var1>255</Var1>
				<Var2>0</Var2>
				<Var3>0</Var3>
				<Var4>0</Var4>
			</CustomVinylTrans>
			<CustomVinylTrans>
				<Hash>-456206930</Hash>
				<Hue1>-799662189</Hue1>
				<Hue2>0</Hue2>
				<Hue3>0</Hue3>
				<Hue4>0</Hue4>
				<Layer>9</Layer>
				<Mir>false</Mir>
				<Rot>139</Rot>
				<Sat1>255</Sat1>
				<Sat2>0</Sat2>
				<Sat3>0</Sat3>
				<Sat4>0</Sat4>
				<ScaleX>147</ScaleX>
				<ScaleY>147</ScaleY>
				<Shear>0</Shear>
				<TranX>-145</TranX>
				<TranY>332</TranY>
				<Var1>255</Var1>
				<Var2>0</Var2>
				<Var3>0</Var3>
				<Var4>0</Var4>
			</CustomVinylTrans>
		</Vinyls>
		<VisualParts>
			<VisualPartTrans>
				<PartHash>-273819714</PartHash>
				<SlotHash>-2126743923</SlotHash>
			</VisualPartTrans>
		</VisualParts>
	</CustomCar>
	<Durability>100</Durability>
	<ExpirationDate i:nil="true"/>
	<Heat>1</Heat>
	<Id>200</Id>
	<OwnershipType>PresetCar</OwnershipType>
</OwnedCarTrans>