<OwnedCarTrans><CustomCar><BaseCar>-87126832</BaseCar><CarClassHash>415909161</CarClassHash><Id>61</Id><IsPreset>true</IsPreset><Level>0</Level><Name>mazdaspeed3</Name><Paints><CustomPaintTrans><Group>47885063</Group><Hue>496032328</Hue><Sat>255</Sat><Slot>0</Slot><Var>209</Var></CustomPaintTrans><CustomPaintTrans><Group>1773701481</Group><Hue>496032328</Hue><Sat>0</Sat><Slot>7</Slot><Var>0</Var></CustomPaintTrans><CustomPaintTrans><Group>1773701481</Group><Hue>496032328</Hue><Sat>0</Sat><Slot>6</Slot><Var>0</Var></CustomPaintTrans><CustomPaintTrans><Group>47885063</Group><Hue>496032328</Hue><Sat>255</Sat><Slot>3</Slot><Var>209</Var></CustomPaintTrans><CustomPaintTrans><Group>47885063</Group><Hue>496032328</Hue><Sat>255</Sat><Slot>4</Slot><Var>209</Var></CustomPaintTrans><CustomPaintTrans><Group>47885063</Group><Hue>496032328</Hue><Sat>255</Sat><Slot>5</Slot><Var>209</Var></CustomPaintTrans></Paints><PerformanceParts><PerformancePartTrans><PerformancePartAttribHash>-788328312</PerformancePartAttribHash></PerformancePartTrans><PerformancePartTrans><PerformancePartAttribHash>-375237073</PerformancePartAttribHash></PerformancePartTrans><PerformancePartTrans><PerformancePartAttribHash>-192032541</PerformancePartAttribHash></PerformancePartTrans><PerformancePartTrans><PerformancePartAttribHash>861836079</PerformancePartAttribHash></PerformancePartTrans><PerformancePartTrans><PerformancePartAttribHash>1236058927</PerformancePartAttribHash></PerformancePartTrans><PerformancePartTrans><PerformancePartAttribHash>1808608237</PerformancePartAttribHash></PerformancePartTrans></PerformanceParts><PhysicsProfileHash>1886825490</PhysicsProfileHash><Rating>281</Rating><ResalePrice>0</ResalePrice><RideHeightDrop>0.75</RideHeightDrop><SkillModParts/><SkillModSlotCount>5</SkillModSlotCount><Version>0</Version><Vinyls><CustomVinylTrans><Hash>-456206931</Hash><Hue1>-799662378</Hue1><Hue2>0</Hue2><Hue3>0</Hue3><Hue4>0</Hue4><Layer>0</Layer><Mir>false</Mir><Rot>0</Rot><Sat1>2</Sat1><Sat2>0</Sat2><Sat3>0</Sat3><Sat4>0</Sat4><ScaleX>262</ScaleX><ScaleY>255</ScaleY><Shear>0</Shear><TranX>87</TranX><TranY>-387</TranY><Var1>207</Var1><Var2>0</Var2><Var3>0</Var3><Var4>0</Var4></CustomVinylTrans><CustomVinylTrans><Hash>-1257777173</Hash><Hue1>-799662384</Hue1><Hue2>0</Hue2><Hue3>0</Hue3><Hue4>0</Hue4><Layer>1</Layer><Mir>false</Mir><Rot>0</Rot><Sat1>0</Sat1><Sat2>0</Sat2><Sat3>0</Sat3><Sat4>0</Sat4><ScaleX>0</ScaleX><ScaleY>0</ScaleY><Shear>0</Shear><TranX>0</TranX><TranY>-5</TranY><Var1>0</Var1><Var2>0</Var2><Var3>0</Var3><Var4>0</Var4></CustomVinylTrans><CustomVinylTrans><Hash>-246667048</Hash><Hue1>-799662452</Hue1><Hue2>0</Hue2><Hue3>0</Hue3><Hue4>0</Hue4><Layer>2</Layer><Mir>false</Mir><Rot>147</Rot><Sat1>0</Sat1><Sat2>0</Sat2><Sat3>0</Sat3><Sat4>0</Sat4><ScaleX>426</ScaleX><ScaleY>426</ScaleY><Shear>0</Shear><TranX>-37</TranX><TranY>311</TranY><Var1>193</Var1><Var2>0</Var2><Var3>0</Var3><Var4>0</Var4></CustomVinylTrans></Vinyls><VisualParts><VisualPartTrans><PartHash>-1874531514</PartHash><SlotHash>-966088147</SlotHash></VisualPartTrans><VisualPartTrans><PartHash>-1674761484</PartHash><SlotHash>-2126743923</SlotHash></VisualPartTrans><VisualPartTrans><PartHash>696489682</PartHash><SlotHash>-1505530948</SlotHash></VisualPartTrans></VisualParts></CustomCar><Durability>100</Durability><ExpirationDate/><Heat>1</Heat><Id>72901896</Id><OwnershipType>PresetCar</OwnershipType></OwnedCarTrans>