<OwnedCarTrans>
	<CustomCar>
		<BaseCar>-691868358</BaseCar>
		<CarClassHash>-406473455</CarClassHash>
		<Id>18869946</Id>
		<IsPreset>true</IsPreset>
		<Level>0</Level>
		<Name>car1022</Name>
		<Paints>
			<CustomPaintTrans>
				<Group>47885063</Group>
				<Hue>496032431</Hue>
				<Sat>0</Sat>
				<Slot>0</Slot>
				<Var>255</Var>
			</CustomPaintTrans>
			<CustomPaintTrans>
				<Group>47885063</Group>
				<Hue>496032431</Hue>
				<Sat>0</Sat>
				<Slot>3</Slot>
				<Var>255</Var>
			</CustomPaintTrans>
			<CustomPaintTrans>
				<Group>47885063</Group>
				<Hue>496032431</Hue>
				<Sat>0</Sat>
				<Slot>4</Slot>
				<Var>255</Var>
			</CustomPaintTrans>
			<CustomPaintTrans>
				<Group>47885063</Group>
				<Hue>496032431</Hue>
				<Sat>0</Sat>
				<Slot>5</Slot>
				<Var>255</Var>
			</CustomPaintTrans>
			<CustomPaintTrans>
				<Group>47885063</Group>
				<Hue>496032431</Hue>
				<Sat>0</Sat>
				<Slot>6</Slot>
				<Var>255</Var>
			</CustomPaintTrans>
			<CustomPaintTrans>
				<Group>47885063</Group>
				<Hue>496032431</Hue>
				<Sat>0</Sat>
				<Slot>7</Slot>
				<Var>255</Var>
			</CustomPaintTrans>
			<CustomPaintTrans>
				<Group>-1480403439</Group>
				<Hue>496032328</Hue>
				<Sat>0</Sat>
				<Slot>1</Slot>
				<Var>255</Var>
			</CustomPaintTrans>
			<CustomPaintTrans>
				<Group>-1480403439</Group>
				<Hue>496032328</Hue>
				<Sat>0</Sat>
				<Slot>2</Slot>
				<Var>255</Var>
			</CustomPaintTrans>
		</Paints>
		<PerformanceParts>
			<PerformancePartTrans>
				<PerformancePartAttribHash>-1847658264</PerformancePartAttribHash>
			</PerformancePartTrans>
			<PerformancePartTrans>
				<PerformancePartAttribHash>-1764235726</PerformancePartAttribHash>
			</PerformancePartTrans>
			<PerformancePartTrans>
				<PerformancePartAttribHash>-1402065015</PerformancePartAttribHash>
			</PerformancePartTrans>
			<PerformancePartTrans>
				<PerformancePartAttribHash>-924298778</PerformancePartAttribHash>
			</PerformancePartTrans>
			<PerformancePartTrans>
				<PerformancePartAttribHash>-350839446</PerformancePartAttribHash>
			</PerformancePartTrans>
			<PerformancePartTrans>
				<PerformancePartAttribHash>-9842941</PerformancePartAttribHash>
			</PerformancePartTrans>
		</PerformanceParts>
		<PhysicsProfileHash>558351072</PhysicsProfileHash>
		<Rating>559</Rating>
		<ResalePrice>282500</ResalePrice>
		<RideHeightDrop>0</RideHeightDrop>
		<SkillModParts/>
		<SkillModSlotCount>6</SkillModSlotCount>
		<Version>0</Version>
		<Vinyls/>
		<VisualParts/>
	</CustomCar>
	<Durability>100</Durability>
	<ExpirationDate i:nil="true"/>
	<Heat>1</Heat>
	<Id>72901281</Id>
	<OwnershipType>PresetCar</OwnershipType>
</OwnedCarTrans>